{
    "waves":  [
                  {
                      "id":  "wave_spiders_01",
                      "displayName":  "Spinnen-Angriff",
                      "enemies":  [
                                      {
                                          "enemyId":  "green_spider",
                                          "count":  5
                                      }
                                  ],
                      "timeBetweenSpawns":  1.5,
                      "loop":  false
                  }
              ]
}
